design/raiz_ASM/control_raiz.v
module control_raiz (
    clk,
    rst,
    in_init,
    in_Q,
    in_K,
    out_S1,
    out_S2,
    out_S3,
    out_S4,
    out_RST,
    out_DONE
);
  input clk;
  input rst;
  input in_init;
  input [15:0] in_Q;
  input in_K;
  output reg out_S1;
  output reg out_S2;
  output reg out_S3;
  output reg out_S4;
  output reg out_RST;
  output reg out_DONE;
  parameter START = 3'b000;
  parameter STEP1 = 3'b001;
  parameter CHECK = 3'b010;
  parameter OPERATE = 3'b011;
  parameter ITERATE = 3'b100;
  parameter DONE = 3'b101;
  parameter STEP2 = 3'b110;

  reg [2:0] state;

  always @(posedge clk) begin
    if (rst) state = START;
    else begin
      case (state)
        START: begin
          state = in_init ? STEP1 : START;
        end
        STEP1:   state = CHECK;
        CHECK: begin
          state = in_Q[15] ? ITERATE : OPERATE;
        end
        OPERATE: state = ITERATE;
        ITERATE: begin
          state = in_K ? DONE : STEP2;
        end
        STEP2:   state = STEP1;
        default: state = START;
      endcase
    end
  end

  always @(*) begin
    case (state)
      START: begin
        out_RST  = 1;
        out_S1   = 0;
        out_S2   = 0;
        out_S3   = 0;
        out_S4   = 0;
        out_DONE = 0;
      end
      STEP1: begin
        out_RST  = 0;
        out_S1   = 1;
        out_S2   = 0;
        out_S3   = 0;
        out_S4   = 0;
        out_DONE = 0;
      end
      CHECK: begin
        out_RST  = 0;
        out_S1   = 0;
        out_S2   = 0;
        out_S3   = 0;
        out_S4   = 0;
        out_DONE = 0;
      end
      OPERATE: begin
        out_RST  = 0;
        out_S1   = 0;
        out_S2   = 1;
        out_S3   = 0;
        out_S4   = 0;
        out_DONE = 0;
      end
      ITERATE: begin
        out_RST  = 0;
        out_S1   = 0;
        out_S2   = 0;
        out_S3   = 1;
        out_S4   = 0;
        out_DONE = 0;
      end
      STEP2: begin
        out_RST  = 0;
        out_S1   = 0;
        out_S2   = 0;
        out_S3   = 0;
        out_S4   = 1;
        out_DONE = 0;
      end
      DONE: begin
        out_RST  = 0;
        out_S1   = 0;
        out_S2   = 0;
        out_S3   = 0;
        out_S4   = 0;
        out_DONE = 1;
      end
      default: begin
        out_RST  = 1;
        out_S1   = 0;
        out_S2   = 0;
        out_S3   = 0;
        out_S4   = 0;
        out_DONE = 0;
      end
    endcase
  end

`ifdef BENCH
  reg [8*40:1] state_name;
  always @(*) begin
    case (state)
      START: state_name = "START";
      STEP1: state_name = "STEP1";
      CHECK: state_name = "CHECK";
      OPERATE: state_name = "OPERATE";
      ITERATE: state_name = "ITERATE";
      STEP2: state_name = "STEP2";
      DONE: state_name = "DONE";
    endcase

  end
`endif

endmodule

design/raiz_ASM/acc.v
module acc (
    clk,
    rst,
    add,
    out_K
);
  input rst;
  input clk;
  input add;
  output reg out_K;
  reg [15:0] N;

  always @(negedge clk) begin
    if (rst) N = 16'd16;
    else begin
      if (add) N = N - 2;
      else begin
        N = N;
      end
    end
  end

  always @(*) out_K = N == 0;
endmodule

design/raiz_ASM/lsrQA.v
module lsrQA (
    clk,
    load,
    shift,
    add,
    in_Q,
    in_RR,
    out_Q
);
  input clk;
  input load;
  input shift;
  input add;
  input [15:0] in_Q;
  input [15:0] in_RR;
  output reg [15:0] out_Q;
  reg [15:0] reg_A;
  always @(negedge clk) begin
    if (load) begin
      out_Q = 15'b0;
      reg_A = in_RR;
    end else begin
      if (shift) {out_Q, reg_A} = ({out_Q, reg_A} << 2);
      else begin
        if (add) out_Q = in_Q;
        else begin
          out_Q = out_Q;
          reg_A = reg_A;
        end
      end
    end
  end
endmodule

design/raiz_ASM/comp.v
module comp (
    in_AUX,
    in_Q,
    out_Q
);

  input [15:0] in_AUX;
  input [15:0] in_Q;
  output reg [15:0] out_Q;


  always @(*) begin
    out_Q = in_Q + (~in_AUX+1);
  end
endmodule

design/raiz_ASM/aux.v
module aux (
    clk,
    load,
    in_R,
    out_AUX
);

  input clk;
  input load;
  input [15:0] in_R;
  output reg [15:0] out_AUX;

  always @(negedge clk) begin
    if (load) out_AUX = in_R << 1 + 1;
    else begin
      out_AUX = out_AUX;
    end
  end
endmodule

design/raiz_ASM/lsrR.v
module lsrR (
    clk,
    rst,
    shift,
    lsb,
    out_R
);
  input clk;
  input rst;
  input shift;
  input lsb;
  output reg [15:0] out_R;

  always @(negedge clk) begin
    if (rst) out_R = 32'b0;
    else begin
      if (shift) out_R = out_R << 1;
      else begin
        if (lsb) out_R[0] = 1;
        else out_R = out_R;
      end
    end
  end
endmodule

design/raiz_ASM/raiz_16.v
module raiz_16 (
    clk,
    rst,
    init,
    in_RR,
    out_Q,
    out_R,
    out_DONE
);
  input rst;
  input clk;
  input init;
  input [15:0] in_RR;

  output [15:0] out_R;
  output [15:0] out_Q;
  output out_DONE;

  wire w_S1;
  wire w_S2;
  wire w_S3;
  wire w_S4;
  wire w_K;
  wire w_RST;
  wire [15:0] w_Q;
  wire [15:0] w_AUX;

  lsrR lsrR (
      .clk  (clk),
      .rst  (rst),
      .shift(w_S4),
      .lsb  (w_S2),
      .out_R(out_R)
  );

  aux aux (
      .clk    (clk),
      .load   (w_S1),
      .in_R   (out_R),
      .out_AUX(w_AUX)
  );

  comp comp (
      .in_AUX(w_AUX),
      .in_Q  (out_Q),
      .out_Q (w_Q)
  );

  lsrQA lsrQA (
      .clk   (clk),
      .load  (rst),
      .shift (w_S1),
      .add   (w_S2),
      .in_Q (w_Q),
      .in_RR (in_RR),
      .out_Q (out_Q)
  );

  acc acc (
      .rst  (rst),
      .clk  (clk),
      .add  (w_S3),
      .out_K(w_K)
  );
  control_raiz control_raiz (
      .clk     (clk),
      .rst     (rst),
      .in_init (init),
      .in_Q    (w_Q),
      .in_K    (w_K),
      .out_S1  (w_S1),
      .out_S2  (w_S2),
      .out_S3  (w_S3),
      .out_S4  (w_S4),
      .out_RST (w_RST),
      .out_DONE(out_DONE)
  );

endmodule

design/raiz_ASM/test_benches/raiz_16_TB.v
`timescale 1ns / 1ps
`define SIMULATION

module raiz_16_TB;
  reg clk;
  reg rst;
  reg start;
  reg [15:0] RR;
  wire [15:0] result;
  wire [15:0] leftover;
  wire done;

  raiz_16 uut (
      .rst     (rst),
      .clk     (clk),
      .init    (start),
      .in_RR   (RR),
      .out_R   (result),
      .out_Q   (leftover),
      .out_DONE(done)
  );

  parameter PERIOD = 20;
  parameter real DUTY_CYCLE = 0.5;
  parameter OFFSET = 0;
  reg [20:0] i;
  event reset_trigger;
  event reset_done_trigger;

  initial begin
    forever begin
      @(reset_trigger);
      @(negedge clk);
      rst = 1;
      repeat (2) @(negedge clk);
      rst = 0;
      ->reset_done_trigger;
    end
  end
  initial begin //Initialize inputs
    clk = 0;
    //rst = 1;
    start = 0;
    RR = 16'h0310;
  end
  initial begin //Process for clk
    #OFFSET;
    forever begin
      clk = 1'b0;
      #(PERIOD - (PERIOD * DUTY_CYCLE)) clk = 1'b1;
      #(PERIOD*DUTY_CYCLE);
    end
  end

  initial begin
    #10 -> reset_trigger;
    @ (reset_done_trigger);
    @ (posedge clk);
    start = 0;
    @ (posedge clk);
    start = 1;

    repeat (2) @(posedge clk);
    start = 0;

    for (i = 0;i<17; i=i+1) begin
      @ (posedge clk);
    end
  end

  initial begin : TEST_CASE
    $dumpfile("raiz_16_TB.vcd");
    $dumpvars(-1, uut);
    #((PERIOD*DUTY_CYCLE)*120) $finish;
  end

endmodule

design/raiz_ASM/simulation/raiz_16_TB.vcd
$date
	Tue Sep 23 08:12:15 2025
$end
$version
	Icarus Verilog
$end
$timescale
	1ps
$end
$scope module raiz_16_TB $end
$scope module uut $end
$var wire 1 ! clk $end
$var wire 16 " in_RR [15:0] $end
$var wire 1 # init $end
$var wire 1 $ rst $end
$var wire 1 % w_S4 $end
$var wire 1 & w_S3 $end
$var wire 1 ' w_S2 $end
$var wire 1 ( w_S1 $end
$var wire 1 ) w_RST $end
$var wire 16 * w_Q [15:0] $end
$var wire 1 + w_K $end
$var wire 16 , w_AUX [15:0] $end
$var wire 16 - out_R [15:0] $end
$var wire 16 . out_Q [15:0] $end
$var wire 1 / out_DONE $end
$scope module acc $end
$var wire 1 ! clk $end
$var wire 1 $ rst $end
$var wire 1 & add $end
$var reg 16 0 N [15:0] $end
$var reg 1 + out_K $end
$upscope $end
$scope module aux $end
$var wire 1 ! clk $end
$var wire 1 ( load $end
$var wire 16 1 in_R [15:0] $end
$var reg 16 2 out_AUX [15:0] $end
$upscope $end
$scope module comp $end
$var wire 16 3 in_AUX [15:0] $end
$var wire 16 4 in_Q [15:0] $end
$var reg 16 5 out_Q [15:0] $end
$upscope $end
$scope module control_raiz $end
$var wire 1 ! clk $end
$var wire 1 + in_K $end
$var wire 16 6 in_Q [15:0] $end
$var wire 1 # in_init $end
$var wire 1 $ rst $end
$var parameter 3 7 CHECK $end
$var parameter 3 8 DONE $end
$var parameter 3 9 ITERATE $end
$var parameter 3 : OPERATE $end
$var parameter 3 ; START $end
$var parameter 3 < STEP1 $end
$var parameter 3 = STEP2 $end
$var reg 1 / out_DONE $end
$var reg 1 ) out_RST $end
$var reg 1 ( out_S1 $end
$var reg 1 ' out_S2 $end
$var reg 1 & out_S3 $end
$var reg 1 % out_S4 $end
$var reg 3 > state [2:0] $end
$var reg 320 ? state_name [320:1] $end
$upscope $end
$scope module lsrQA $end
$var wire 1 ' add $end
$var wire 1 ! clk $end
$var wire 16 @ in_Q [15:0] $end
$var wire 16 A in_RR [15:0] $end
$var wire 1 $ load $end
$var wire 1 ( shift $end
$var reg 16 B out_Q [15:0] $end
$var reg 16 C reg_A [15:0] $end
$upscope $end
$scope module lsrR $end
$var wire 1 ! clk $end
$var wire 1 ' lsb $end
$var wire 1 $ rst $end
$var wire 1 % shift $end
$var reg 16 D out_R [15:0] $end
$upscope $end
$upscope $end
$upscope $end
$enddefinitions $end
$comment Show the parameter values. $end
$dumpall
b110 =
b1 <
b0 ;
b11 :
b100 9
b101 8
b10 7
$end
#0
$dumpvars
bx D
bx C
bx B
b1100010000 A
bx @
bx ?
bx >
bx 6
bx 5
bx 4
bx 3
bx 2
bx 1
bx 0
x/
bx .
bx -
bx ,
x+
bx *
x)
x(
x'
x&
x%
x$
0#
b1100010000 "
0!
$end
#10000
b101001101010100010000010101001001010100 ?
0/
0%
0&
0'
0(
1)
b0 >
1!
#20000
0+
b10000 0
b1100010000 C
b0 .
b0 4
b0 B
b0 -
b0 1
b0 D
1$
0!
#30000
1!
#40000
0!
#50000
1!
#60000
0$
0!
#70000
1!
#80000
0!
#90000
1#
1!
#100000
0!
#110000
1(
0)
b101001101010100010001010101000000110001 ?
b1 >
1!
#120000
b1111111111111111 *
b1111111111111111 5
b1111111111111111 6
b1111111111111111 @
b1 ,
b1 2
b1 3
b110001000000 C
0!
#130000
b100001101001000010001010100001101001011 ?
0(
0#
b10 >
1!
#140000
0!
#150000
1&
b1001001010101000100010101010010010000010101010001000101 ?
b100 >
1!
#160000
b1110 0
0!
#170000
b101001101010100010001010101000000110010 ?
1%
0&
b110 >
1!
#180000
0!
#190000
0%
1(
b101001101010100010001010101000000110001 ?
b1 >
1!
#200000
b11000100000000 C
0!
#210000
b100001101001000010001010100001101001011 ?
0(
b10 >
1!
#220000
0!
#230000
1&
b1001001010101000100010101010010010000010101010001000101 ?
b100 >
1!
#240000
b1100 0
0!
#250000
b101001101010100010001010101000000110010 ?
1%
0&
b110 >
1!
#260000
0!
#270000
0%
1(
b101001101010100010001010101000000110001 ?
b1 >
1!
#280000
b1100010000000000 C
0!
#290000
b100001101001000010001010100001101001011 ?
0(
b10 >
1!
#300000
0!
#310000
1&
b1001001010101000100010101010010010000010101010001000101 ?
b100 >
1!
#320000
b1010 0
0!
#330000
b101001101010100010001010101000000110010 ?
1%
0&
b110 >
1!
#340000
0!
#350000
0%
1(
b101001101010100010001010101000000110001 ?
b1 >
1!
#360000
b10 *
b10 5
b10 6
b10 @
b11 .
b11 4
b11 B
b1000000000000 C
0!
#370000
b100001101001000010001010100001101001011 ?
0(
b10 >
1!
#380000
0!
#390000
1'
b1001111010100000100010101010010010000010101010001000101 ?
b11 >
1!
#400000
b1 *
b1 5
b1 6
b1 @
b1 -
b1 1
b1 D
b10 .
b10 4
b10 B
0!
#410000
b1001001010101000100010101010010010000010101010001000101 ?
1&
0'
b100 >
1!
#420000
b1000 0
0!
#430000
1%
0&
b101001101010100010001010101000000110010 ?
b110 >
1!
#440000
b10 -
b10 1
b10 D
0!
#450000
b101001101010100010001010101000000110001 ?
0%
1(
b1 >
1!
#460000
b11 *
b11 5
b11 6
b11 @
b1000 .
b1000 4
b1000 B
b100000000000000 C
b101 ,
b101 2
b101 3
0!
#470000
0(
b100001101001000010001010100001101001011 ?
b10 >
1!
#480000
0!
#490000
b1001111010100000100010101010010010000010101010001000101 ?
1'
b11 >
1!
#500000
b1111111111111110 *
b1111111111111110 5
b1111111111111110 6
b1111111111111110 @
b11 .
b11 4
b11 B
b11 -
b11 1
b11 D
0!
#510000
1&
0'
b1001001010101000100010101010010010000010101010001000101 ?
b100 >
1!
#520000
b110 0
0!
#530000
b101001101010100010001010101000000110010 ?
1%
0&
b110 >
1!
#540000
b110 -
b110 1
b110 D
0!
#550000
0%
1(
b101001101010100010001010101000000110001 ?
b1 >
1!
#560000
b0 *
b0 5
b0 6
b0 @
b1101 ,
b1101 2
b1101 3
b1101 .
b1101 4
b1101 B
b0 C
0!
#570000
b100001101001000010001010100001101001011 ?
0(
b10 >
1!
#580000
0!
#590000
1'
b1001111010100000100010101010010010000010101010001000101 ?
b11 >
1!
#600000
b1111111111110011 *
b1111111111110011 5
b1111111111110011 6
b1111111111110011 @
b111 -
b111 1
b111 D
b0 .
b0 4
b0 B
0!
#610000
b1001001010101000100010101010010010000010101010001000101 ?
1&
0'
b100 >
1!
#620000
b100 0
0!
#630000
1%
0&
b101001101010100010001010101000000110010 ?
b110 >
1!
#640000
b1110 -
b1110 1
b1110 D
0!
#650000
b101001101010100010001010101000000110001 ?
0%
1(
b1 >
1!
#660000
b1111111111100011 *
b1111111111100011 5
b1111111111100011 6
b1111111111100011 @
b11101 ,
b11101 2
b11101 3
0!
#670000
0(
b100001101001000010001010100001101001011 ?
b10 >
1!
#680000
0!
#690000
b1001001010101000100010101010010010000010101010001000101 ?
1&
b100 >
1!
#700000
b10 0
0!
#710000
1%
0&
b101001101010100010001010101000000110010 ?
b110 >
1!
#720000
b11100 -
b11100 1
b11100 D
0!
#730000
b101001101010100010001010101000000110001 ?
0%
1(
b1 >
1!
#740000
b1111111111000111 *
b1111111111000111 5
b1111111111000111 6
b1111111111000111 @
b111001 ,
b111001 2
b111001 3
0!
#750000
0(
b100001101001000010001010100001101001011 ?
b10 >
1!
#760000
0!
#770000
b1001001010101000100010101010010010000010101010001000101 ?
1&
b100 >
1!
#780000
1+
b0 0
0!
#790000
1/
0&
b1000100010011110100111001000101 ?
b101 >
1!
#800000
0!
#810000
b101001101010100010000010101001001010100 ?
0/
1)
b0 >
1!
