design/raiz_ASM/control_raiz.v
module control_raiz (
    clk,
    rst,
    in_init,
    in_Z,
    in_K,
    out_S1,
    out_S2,
    out_S3,
    out_S4,
    out_RST,
    out_DONE
);
  input clk;
  input rst;
  input in_init;
  input in_Z;
  input in_K;
  output reg out_S1;
  output reg out_S2;
  output reg out_S3;
  output reg out_S4;
  output reg out_RST;
  output reg out_DONE;
  parameter START = 3'b000;
  parameter STEP1 = 3'b001;
  parameter CHECK = 3'b010;
  parameter OPERATE = 3'b011;
  parameter ITERATE = 3'b100;
  parameter DONE = 3'b101;
  parameter STEP2 = 3'b110;

  reg [2:0] state;

  always @(posedge clk) begin
    if (rst) state = START;
    else begin
      case (state)
        START: begin
          state = in_init ? STEP1 : START;
        end
        STEP1:   state = CHECK;
        CHECK: begin
          state = in_Z ? OPERATE : ITERATE;
        end
        OPERATE: state = ITERATE;
        ITERATE: begin
          state = in_K ? DONE : STEP2;
        end
        STEP2:   state = STEP1;
        default: state = START;
      endcase
    end
  end

  always @(*) begin
    case (state)
      START: begin
        out_RST  = 1;
        out_S1   = 0;
        out_S2   = 0;
        out_S3   = 0;
        out_S4   = 0;
        out_DONE = 0;
      end
      STEP1: begin
        out_RST  = 0;
        out_S1   = 1;
        out_S2   = 0;
        out_S3   = 0;
        out_S4   = 0;
        out_DONE = 0;
      end
      CHECK: begin
        out_RST  = 0;
        out_S1   = 0;
        out_S2   = 0;
        out_S3   = 0;
        out_S4   = 0;
        out_DONE = 0;
      end
      OPERATE: begin
        out_RST  = 0;
        out_S1   = 0;
        out_S2   = 1;
        out_S3   = 0;
        out_S4   = 0;
        out_DONE = 0;
      end
      ITERATE: begin
        out_RST  = 0;
        out_S1   = 0;
        out_S2   = 0;
        out_S3   = 1;
        out_S4   = 0;
        out_DONE = 0;
      end
      STEP2: begin
        out_RST  = 0;
        out_S1   = 0;
        out_S2   = 0;
        out_S3   = 0;
        out_S4   = 1;
        out_DONE = 0;
      end
      DONE: begin
        out_RST  = 0;
        out_S1   = 0;
        out_S2   = 0;
        out_S3   = 0;
        out_S4   = 0;
        out_DONE = 1;
      end
      default: begin
        out_RST  = 1;
        out_S1   = 0;
        out_S2   = 0;
        out_S3   = 0;
        out_S4   = 0;
        out_DONE = 0;
      end
    endcase
  end

`ifdef BENCH
  reg [8*40:1] state_name;
  always @(*) begin
    case (state)
      START: state_name = "START";
      STEP1: state_name = "STEP1";
      CHECK: state_name = "CHECK";
      OPERATE: state_name = "OPERATE";
      ITERATE: state_name = "ITERATE";
      STEP2: state_name = "STEP2";
      DONE: state_name = "DONE";
    endcase

  end
`endif

endmodule

design/raiz_ASM/acc.v
module acc (
    clk,
    rst,
    add,
    out_K
);
  input rst;
  input clk;
  input add;
  output reg out_K;
  reg [15:0] N;

  always @(negedge clk) begin
    if (rst) N = 16'd16;
    else begin
      if (add) N = N - 2;
      else begin
        N = N;
      end
    end
  end

  always @(*) out_K = N == 0;
endmodule

design/raiz_ASM/lsrQA.v
module lsrQA (
    clk,
    load,
    shift,
    add,
    in_AUX,
    in_RR,
    out_Q
);
  input clk;
  input load;
  input shift;
  input add;
  input [15:0] in_AUX;
  input [15:0] in_RR;
  output reg [15:0] out_Q;
  reg [15:0] reg_A;
  always @(negedge clk) begin
    if (load) begin
      out_Q = 15'b0;
      reg_A = in_RR;
    end else begin
      if (shift) {out_Q, reg_A} = {out_Q, reg_A} << 2;
      else begin
        if (add) out_Q = out_Q + (~in_AUX + 1);
        else begin
          out_Q = out_Q;
          reg_A = reg_A;
        end
      end
    end
  end
endmodule

design/raiz_ASM/comp.v
module comp (
    in_AUX,
    in_Q,
    z
);

  input [15:0] in_AUX;
  input [15:0] in_Q;
  output z;
  reg tmp;
  initial tmp = 0;
  assign z = tmp;
  always @(*) tmp = in_Q >= in_AUX;
endmodule

design/raiz_ASM/aux.v
module aux (
    clk,
    load,
    in_R,
    out_AUX
);

  input clk;
  input load;
  input [15:0] in_R;
  output reg [15:0] out_AUX;

  always @(negedge clk) begin
    if (load) out_AUX = in_R << 1 + 1;
    else begin
      out_AUX = out_AUX;
    end
  end
endmodule

design/raiz_ASM/lsrR.v
module lsrR (
    clk,
    rst,
    shift,
    lsb,
    out_R
);
  input clk;
  input rst;
  input shift;
  input lsb;
  output reg [15:0] out_R;

  always @(negedge clk) begin
    if (rst) out_R = 32'b0;
    else begin
      if (shift) out_R = out_R << 1;
      else begin
        if (lsb) out_R[0] = 1;
        else out_R = out_R;
      end
    end
  end
endmodule

design/raiz_ASM/raiz_16.v
module raiz_16 (
    clk,
    rst,
    init,
    in_RR,
    out_Q,
    out_R,
    out_done
);
  input rst;
  input clk;
  input init;
  input [15:0] in_RR;

  output [15:0] out_R;
  output [15:0] out_Q;
  output out_done;

  wire w_S1;
  wire w_S2;
  wire w_S3;
  wire w_S4;
  wire w_Z;
  wire w_K;
  wire w_RST;
  wire [15:0] w_AUX;

  lsrR lsrR (
      .clk  (clk),
      .rst  (rst),
      .shift(w_S4),
      .lsb  (w_S2),
      .out_R(out_R)
  );

  aux aux (
      .clk    (clk),
      .load   (w_S1),
      .in_R   (out_R),
      .out_AUX(w_AUX)
  );

  comp comp (
      .in_AUX(w_AUX),
      .in_Q  (out_Q),
      .z     (w_Z)
  );

  lsrQA lsrQA (
      .clk   (clk),
      .load  (rst),
      .shift (w_S1),
      .add   (w_S2),
      .in_AUX(w_AUX),
      .in_RR (in_RR),
      .out_Q (out_Q)
  );

  acc acc (
      .rst  (rst),
      .clk  (clk),
      .add  (w_S3),
      .out_K(w_K)
  );
  control_raiz control_raiz (
      .clk     (clk),
      .rst     (rst),
      .in_init (init),
      .in_Z    (w_Z),
      .in_K    (w_K),
      .out_S1  (w_S1),
      .out_S2  (w_S2),
      .out_S3  (w_S3),
      .out_S4  (w_S4),
      .out_RST (w_RST),
      .out_DONE(out_done)
  );

endmodule

design/raiz_ASM/test_benches/raiz_16_TB.v
`timescale 1ns / 1ps
`define SIMULATION

module raiz_16_TB;
  reg clk;
  reg rst;
  reg start;
  reg [15:0] RR;
  wire [15:0] result;
  wire [15:0] leftover;
  wire done;

  raiz_16 uut (
      .rst     (rst),
      .clk     (clk),
      .init    (start),
      .in_RR   (RR),
      .out_R   (result),
      .out_Q   (leftover),
      .out_DONE(done)
  );

  parameter PERIOD = 20;
  parameter real DUTY_CYCLE = 0.5;
  parameter OFFSET = 0;
  reg [20:0] i;
  event reset_trigger;
  event reset_done_trigger;

  initial begin
    forever begin
      @(reset_trigger);
      @(negedge clk);
      rst = 1;
      repeat (2) @(negedge clk);
      rst = 0;
      ->reset_done_trigger;
    end
  end
  initial begin //Initialize inputs
    clk = 0;
    //rst = 1;
    start = 0;
    RR = 16'h0310;
  end
  initial begin //Process for clk
    #OFFSET;
    forever begin
      clk = 1'b0;
      #(PERIOD - (PERIOD * DUTY_CYCLE)) clk = 1'b1;
      #(PERIOD*DUTY_CYCLE);
    end
  end

  initial begin
    #10 -> reset_trigger;
    @ (reset_done_trigger);
    @ (posedge clk);
    start = 0;
    @ (posedge clk);
    start = 1;

    repeat (2) @(posedge clk);
    start = 0;

    for (i = 0;i<17; i=i+1) begin
      @ (posedge clk);
    end
  end

  initial begin : TEST_CASE
    $dumpfile("raiz_16_TB.vcd");
    $dumpvars(-1, uut);
    #((PERIOD*DUTY_CYCLE)*120) $finish;
  end

endmodule

design/raiz_ASM/simulation/raiz_16_TB.vcd
$date
	Tue Sep 23 07:19:50 2025
$end
$version
	Icarus Verilog
$end
$timescale
	1ps
$end
$scope module raiz_16_TB $end
$scope module uut $end
$var wire 1 ! clk $end
$var wire 16 " in_RR [15:0] $end
$var wire 1 # init $end
$var wire 1 $ rst $end
$var wire 1 % w_Z $end
$var wire 1 & w_S4 $end
$var wire 1 ' w_S3 $end
$var wire 1 ( w_S2 $end
$var wire 1 ) w_S1 $end
$var wire 1 * w_RST $end
$var wire 1 + w_K $end
$var wire 16 , w_AUX [15:0] $end
$var wire 1 - out_done $end
$var wire 16 . out_R [15:0] $end
$var wire 16 / out_Q [15:0] $end
$scope module acc $end
$var wire 1 ! clk $end
$var wire 1 $ rst $end
$var wire 1 ' add $end
$var reg 16 0 N [15:0] $end
$var reg 1 + out_K $end
$upscope $end
$scope module aux $end
$var wire 1 ! clk $end
$var wire 1 ) load $end
$var wire 16 1 in_R [15:0] $end
$var reg 16 2 out_AUX [15:0] $end
$upscope $end
$scope module comp $end
$var wire 16 3 in_AUX [15:0] $end
$var wire 1 % z $end
$var wire 16 4 in_Q [15:0] $end
$var reg 1 5 tmp $end
$upscope $end
$scope module control_raiz $end
$var wire 1 ! clk $end
$var wire 1 + in_K $end
$var wire 1 % in_Z $end
$var wire 1 # in_init $end
$var wire 1 $ rst $end
$var parameter 3 6 CHECK $end
$var parameter 3 7 DONE $end
$var parameter 3 8 ITERATE $end
$var parameter 3 9 OPERATE $end
$var parameter 3 : START $end
$var parameter 3 ; STEP1 $end
$var parameter 3 < STEP2 $end
$var reg 1 - out_DONE $end
$var reg 1 * out_RST $end
$var reg 1 ) out_S1 $end
$var reg 1 ( out_S2 $end
$var reg 1 ' out_S3 $end
$var reg 1 & out_S4 $end
$var reg 3 = state [2:0] $end
$var reg 320 > state_name [320:1] $end
$upscope $end
$scope module lsrQA $end
$var wire 1 ( add $end
$var wire 1 ! clk $end
$var wire 16 ? in_AUX [15:0] $end
$var wire 16 @ in_RR [15:0] $end
$var wire 1 $ load $end
$var wire 1 ) shift $end
$var reg 16 A out_Q [15:0] $end
$var reg 16 B reg_A [15:0] $end
$upscope $end
$scope module lsrR $end
$var wire 1 ! clk $end
$var wire 1 ( lsb $end
$var wire 1 $ rst $end
$var wire 1 & shift $end
$var reg 16 C out_R [15:0] $end
$upscope $end
$upscope $end
$upscope $end
$enddefinitions $end
$comment Show the parameter values. $end
$dumpall
b110 <
b1 ;
b0 :
b11 9
b100 8
b101 7
b10 6
$end
#0
$dumpvars
bx C
bx B
bx A
b10000 @
bx ?
bx >
bx =
05
bx 4
bx 3
bx 2
bx 1
bx 0
bx /
bx .
x-
bx ,
x+
x*
x)
x(
x'
x&
0%
x$
0#
b10000 "
0!
$end
#10000
b101001101010100010000010101001001010100 >
0-
0&
0'
0(
0)
1*
b0 =
1!
#20000
0+
x%
x5
b10000 0
b10000 B
b0 /
b0 4
b0 A
b0 .
b0 1
b0 C
1$
0!
#30000
1!
#40000
0!
#50000
1!
#60000
0$
0!
#70000
1!
#80000
0!
#90000
1#
1!
#100000
0!
#110000
1)
0*
b101001101010100010001010101000000110001 >
b1 =
1!
#120000
0%
05
b1 ,
b1 2
b1 3
b1 ?
b1000000 B
0!
#130000
b100001101001000010001010100001101001011 >
0)
0#
b10 =
1!
#140000
0!
#150000
1'
b1001001010101000100010101010010010000010101010001000101 >
b100 =
1!
#160000
b1110 0
0!
#170000
b101001101010100010001010101000000110010 >
1&
0'
b110 =
1!
#180000
0!
#190000
0&
1)
b101001101010100010001010101000000110001 >
b1 =
1!
#200000
b100000000 B
0!
#210000
b100001101001000010001010100001101001011 >
0)
b10 =
1!
#220000
0!
#230000
1'
b1001001010101000100010101010010010000010101010001000101 >
b100 =
1!
#240000
b1100 0
0!
#250000
b101001101010100010001010101000000110010 >
1&
0'
b110 =
1!
#260000
0!
#270000
0&
1)
b101001101010100010001010101000000110001 >
b1 =
1!
#280000
b10000000000 B
0!
#290000
b100001101001000010001010100001101001011 >
0)
b10 =
1!
#300000
0!
#310000
1'
b1001001010101000100010101010010010000010101010001000101 >
b100 =
1!
#320000
b1010 0
0!
#330000
b101001101010100010001010101000000110010 >
1&
0'
b110 =
1!
#340000
0!
#350000
0&
1)
b101001101010100010001010101000000110001 >
b1 =
1!
#360000
b1000000000000 B
0!
#370000
b100001101001000010001010100001101001011 >
0)
b10 =
1!
#380000
0!
#390000
1'
b1001001010101000100010101010010010000010101010001000101 >
b100 =
1!
#400000
b1000 0
0!
#410000
b101001101010100010001010101000000110010 >
1&
0'
b110 =
1!
#420000
0!
#430000
0&
1)
b101001101010100010001010101000000110001 >
b1 =
1!
#440000
b100000000000000 B
0!
#450000
b100001101001000010001010100001101001011 >
0)
b10 =
1!
#460000
0!
#470000
1'
b1001001010101000100010101010010010000010101010001000101 >
b100 =
1!
#480000
b110 0
0!
#490000
b101001101010100010001010101000000110010 >
1&
0'
b110 =
1!
#500000
0!
#510000
0&
1)
b101001101010100010001010101000000110001 >
b1 =
1!
#520000
1%
15
b1 /
b1 4
b1 A
b0 B
0!
#530000
b100001101001000010001010100001101001011 >
0)
b10 =
1!
#540000
0!
#550000
1(
b1001111010100000100010101010010010000010101010001000101 >
b11 =
1!
#560000
0%
05
b1 .
b1 1
b1 C
b0 /
b0 4
b0 A
0!
#570000
b1001001010101000100010101010010010000010101010001000101 >
1'
0(
b100 =
1!
#580000
b100 0
0!
#590000
1&
0'
b101001101010100010001010101000000110010 >
b110 =
1!
#600000
b10 .
b10 1
b10 C
0!
#610000
b101001101010100010001010101000000110001 >
0&
1)
b1 =
1!
#620000
b101 ,
b101 2
b101 3
b101 ?
0!
#630000
0)
b100001101001000010001010100001101001011 >
b10 =
1!
#640000
0!
#650000
b1001001010101000100010101010010010000010101010001000101 >
1'
b100 =
1!
#660000
b10 0
0!
#670000
1&
0'
b101001101010100010001010101000000110010 >
b110 =
1!
#680000
b100 .
b100 1
b100 C
0!
#690000
b101001101010100010001010101000000110001 >
0&
1)
b1 =
1!
#700000
b1001 ,
b1001 2
b1001 3
b1001 ?
0!
#710000
0)
b100001101001000010001010100001101001011 >
b10 =
1!
#720000
0!
#730000
b1001001010101000100010101010010010000010101010001000101 >
1'
b100 =
1!
#740000
1+
b0 0
0!
#750000
1-
0'
b1000100010011110100111001000101 >
b101 =
1!
#760000
0!
#770000
b101001101010100010000010101001001010100 >
0-
1*
b0 =
1!
