design/BCD_ASM/control_BCD.v
module control_BCD (
    clk,
    rst,
    in_init,
    in_K,
    in_sum_UND,
    in_sum_DEC,
    out_S1,
    out_S2,
    out_S3,
    out_S4,
    out_S5,
    out_RST,
    out_DONE
);
  input clk;
  input rst;
  input in_init;
  input in_K;
  input [3:0] in_sum_UND;
  input [3:0] in_sum_DEC;
  output reg out_S1;
  output reg out_S2;
  output reg out_S3;
  output reg out_S4;
  output reg out_S5;
  output reg out_RST;
  output reg out_DONE;

  parameter START = 4'b0000;
  parameter SHIFT = 4'b0001;
  parameter CHECK_NEG = 4'b0010;
  parameter LOAD_UND = 4'b0011;
  parameter LOAD_DEC = 4'b0100;
  parameter LOAD_ALL = 4'b0101;
  parameter ITERATE = 4'b0110;
  parameter LAST_SHIFT = 4'b0111;
  parameter DONE = 4'b1000;
  reg [3:0] state;

  parameter GE_NEG_UND = 2'b10;  //Negate Great Equal  UND 0 if UND>=5
  parameter GE_NEG_DEC = 2'b01;  //Negate Great Equal  DEC 0 if UND>=5
  parameter GE_NEG_ALL = 2'b00;  //MSB:DEC, LBS:UND
  parameter GE_NEG_NONE = 2'b11;

  always @(posedge clk) begin
    if (rst) state = START;
    else begin
      case (state)
        START: state = in_init ? SHIFT : START;
        SHIFT: begin
          state = CHECK_NEG;
        end
        CHECK_NEG: begin
          case ({
            in_sum_DEC[3], in_sum_UND[3]
          })
            GE_NEG_NONE: state = ITERATE;
            GE_NEG_UND:  state = LOAD_UND;
            GE_NEG_DEC:  state = LOAD_DEC;
            GE_NEG_ALL:  state = LOAD_ALL;
          endcase
        end
        LOAD_UND, LOAD_DEC, LOAD_ALL: state = ITERATE;
        ITERATE: state = in_K ? LAST_SHIFT : SHIFT;
        LAST_SHIFT: state = DONE;
        DONE: state = START;
        default: state = START;
      endcase
    end
  end

  always @(*) begin
    case (state)
      START: begin
        out_RST  = 1;
        out_S1   = 0;
        out_S2   = 0;
        out_S3   = 0;
        out_S4   = 0;
        out_S5   = 0;
        out_DONE = 0;
      end
      SHIFT: begin
        out_RST  = 0;
        out_S1   = 1;
        out_S2   = 0;
        out_S3   = 0;
        out_S4   = 0;
        out_S5   = 0;
        out_DONE = 0;
      end
      CHECK_NEG: begin
        out_RST  = 0;
        out_S1   = 0;
        out_S2   = 0;
        out_S3   = 0;
        out_S4   = 0;
        out_S5   = 0;
        out_DONE = 0;
      end
      LOAD_UND: begin
        out_RST  = 0;
        out_S1   = 0;
        out_S2   = 1;
        out_S3   = 1;
        out_S4   = 0;
        out_S5   = 0;
        out_DONE = 0;
      end
      LOAD_DEC: begin
        out_RST  = 0;
        out_S1   = 0;
        out_S2   = 1;
        out_S3   = 0;
        out_S4   = 1;
        out_S5   = 0;
        out_DONE = 0;
      end
      LOAD_ALL: begin
        out_RST  = 0;
        out_S1   = 0;
        out_S2   = 1;
        out_S3   = 1;
        out_S4   = 1;
        out_S5   = 0;
        out_DONE = 0;
      end
      ITERATE: begin
        out_RST  = 0;
        out_S1   = 0;
        out_S2   = 0;
        out_S3   = 0;
        out_S4   = 0;
        out_S5   = 1;
        out_DONE = 0;
      end
      LAST_SHIFT: begin
        out_RST  = 0;
        out_S1   = 1;
        out_S2   = 0;
        out_S3   = 0;
        out_S4   = 0;
        out_S5   = 0;
        out_DONE = 0;
      end
      DONE: begin
        out_RST  = 0;
        out_S1   = 0;
        out_S2   = 0;
        out_S3   = 0;
        out_S4   = 0;
        out_S5   = 0;
        out_DONE = 1;
      end
    endcase
  end

`ifdef BENCH
  reg [8*40:1] state_name;
  reg [8*40:1] state_comp_name;
  always @(*) begin
    case (state)
      START: state_name = "START";
      SHIFT: state_name = "SHIFT";
      CHECK_NEG: state_name = "CHECK_NEG";
      PRE_LOAD_UND: state_name = "PRE_LOAD_UND";
      PRE_LOAD_DEC: state_name = "PRE_LOAD_DEC";
      PRE_LOAD_ALL: state_name = "PRE_LOAD_ALL";
      LOAD_UND: state_name = "LOAD_UND";
      LOAD_DEC: state_name = "LOAD_DEC";
      LOAD_ALL: state_name = "LOAD_ALL";
      ITERATE: state_name = "ITERATE";
      LAST_SHIFT: state_name = "LAST_SHIFT";
      DONE: state_name = "DONE";
    endcase
  end
`endif

endmodule

design/BCD_ASM/acc.v
module acc (
    clk,
    rst,
    add,
    out_K
);
  input rst;
  input clk;
  input add;
  output reg out_K;
  reg [3:0] N;

  always @(negedge clk) begin
    if (rst) N = 4'h8;
    else begin
      if (add) N = N - 1;
      else begin
        N = N;
      end
    end
  end

  always @(*) out_K = N == 0;
endmodule

design/BCD_ASM/sum.v
module sum (A,B, out);
input [3:0] A;
input [3:0] B;
output reg [3:0] out;

always @(*) out = A + B;

endmodule

design/rtl/raw_implementation/BCD_ASM/mux.v
module mux (
    SELECT,
    out
);
  input SELECT;
  output reg [3:0] out;
  //                              3         -5
  always @(*) out = SELECT ? 4'b0011 : 4'b1011;

endmodule

design/rtl/raw_implementation/BCD_ASM/lsr_CEN_DEC_UND_BIN.v
module lsr_CEN_DEC_UND_BIN (
    clk,
    load_BIN,
    shift,
    load_UND,
    load_DEC,
    in_BIN,
    in_UND,
    in_DEC,
    out_UND,
    out_DEC,
    out_CEN
);
  input clk;
  input load_BIN;
  input shift;
  input load_UND;
  input load_DEC;
  input [8:0] in_BIN;
  input [3:0] in_UND;
  input [3:0] in_DEC;
  output reg [3:0] out_UND;
  output reg [3:0] out_DEC;
  output reg [3:0] out_CEN;
  reg [8:0] reg_BIN;
  always @(negedge clk) begin
    if (load_BIN) begin
      reg_BIN = in_BIN;
      out_UND = 4'h0;
      out_DEC = 4'h0;
      out_CEN = 4'h0;
    end else begin
      if (shift) {out_CEN, out_DEC, out_UND, reg_BIN} = {out_CEN, out_DEC, out_UND, reg_BIN} << 1;
      else begin
        if (load_UND) out_UND = in_UND;
        if (load_DEC) out_DEC = in_DEC;
        else begin
          reg_BIN = reg_BIN;
          out_UND = out_UND;
          out_DEC = out_DEC;
          out_CEN = out_CEN;
        end
      end
    end
  end


endmodule

design/BCD_ASM/BCD.v
module BCD (
    clk,
    rst,
    init,
    in_BIN,
    out_UND,
    out_DEC,
    out_CEN,
    out_DONE
);
  input rst;
  input clk;
  input init;
  input [8:0] in_BIN;
  output [3:0] out_UND;
  output [3:0] out_DEC;
  output [3:0] out_CEN;
  output out_DONE;
  wire w_S1;
  wire w_S2;
  wire w_S3;
  wire w_S4;
  wire w_S5;
  wire w_RST;
  wire w_K;
  wire [3:0] w_sum_UND;
  wire [3:0] w_sum_DEC;
  wire [3:0] w_mux_UND;
  wire [3:0] w_mux_DEC;


  lsr_CEN_DEC_UND_BIN lsr_CEN_DEC_UND_BIN (
      .clk     (clk),
      .load_BIN(w_RST),
      .shift   (w_S1),
      .load_UND(w_S3),
      .load_DEC(w_S4),
      .in_BIN  (in_BIN),
      .in_UND  (w_sum_UND),
      .in_DEC  (w_sum_DEC),
      .out_UND (out_UND),
      .out_DEC (out_DEC),
      .out_CEN (out_CEN)
  );

  mux mux_UND (
      .SELECT(w_S2),
      .out   (w_mux_UND)
  );
  mux mux_DEV (
      .SELECT(w_S2),
      .out   (w_mux_DEC)
  );

  sum sum_UND (
      .A  (out_UND),
      .B  (w_mux_UND),
      .out(w_sum_UND)
  );
  sum sum_DEC (
      .A  (out_DEC),
      .B  (w_mux_DEC),
      .out(w_sum_DEC)
  );

  acc acc (
      .rst  (w_RST),
      .clk  (clk),
      .add  (w_S5),
      .out_K(w_K)
  );

  control_BCD control_BCD (
      .clk       (clk),
      .rst       (rst),
      .in_init   (init),
      .in_K      (w_K),
      .in_sum_UND(w_sum_UND),
      .in_sum_DEC(w_sum_DEC),
      .out_S1    (w_S1),
      .out_S2    (w_S2),
      .out_S3    (w_S3),
      .out_S4    (w_S4),
      .out_S5    (w_S5),
      .out_RST   (w_RST),
      .out_DONE  (out_DONE)
  );




endmodule

design/BCD_ASM/test_benches/BIN_TO_BCD_TB.v
`timescale 1ns / 1ps
`define SIMULATION

module BCD_TB;

  reg clk;
  reg rst;
  reg start;
  reg [8:0] BIN;
  wire [3:0] UND;
  wire [3:0] DEC;
  wire [3:0] CEN;
  wire done;

  BCD uut (
      .rst     (rst),
      .clk     (clk),
      .init    (start),
      .in_BIN  (BIN),
      .out_UND (UND),
      .out_DEC (DEC),
      .out_CEN (CEN),
      .out_DONE(DONE)
  );

  parameter PERIOD = 20;
  parameter real DUTY_CYCLE = 0.5;
  parameter OFFSET = 0;
  reg [20:0] i;
  event reset_trigger;
  event reset_done_trigger;

  initial begin
    forever begin
      @(reset_trigger);
      @(negedge clk);
      rst = 1;
      repeat (2) @(negedge clk);
      rst = 0;
      ->reset_done_trigger;
    end
  end
  initial begin //Initialize inputs
    clk = 0;
    //rst = 1;
    start = 0;
    BIN = 9'b111111111;
  end
  initial begin //Process for clk
    #OFFSET;
    forever begin
      clk = 1'b0;
      #(PERIOD - (PERIOD * DUTY_CYCLE)) clk = 1'b1;
      #(PERIOD*DUTY_CYCLE);
    end
  end

  initial begin
    #10 -> reset_trigger;
    @ (reset_done_trigger);
    @ (posedge clk);
    start = 0;
    @ (posedge clk);
    start = 1;

    repeat (2) @(posedge clk);
    start = 0;

    for (i = 0;i<17; i=i+1) begin
      @ (posedge clk);
    end
  end

  initial begin : TEST_CASE
    $dumpfile("BCD_TB.vcd");
    $dumpvars(-1, uut);
    #((PERIOD*DUTY_CYCLE)*120) $finish;
  end

endmodule

design/BCD_ASM/simulation/BCD_TB.vcd
$date
	Tue Sep 23 20:55:04 2025
$end
$version
	Icarus Verilog
$end
$timescale
	1ps
$end
$scope module BCD_TB $end
$scope module uut $end
$var wire 1 ! clk $end
$var wire 9 " in_BIN [8:0] $end
$var wire 1 # init $end
$var wire 1 $ rst $end
$var wire 4 % w_sum_UND [3:0] $end
$var wire 4 & w_sum_DEC [3:0] $end
$var wire 4 ' w_mux_UND [3:0] $end
$var wire 4 ( w_mux_DEC [3:0] $end
$var wire 1 ) w_S5 $end
$var wire 1 * w_S4 $end
$var wire 1 + w_S3 $end
$var wire 1 , w_S2 $end
$var wire 1 - w_S1 $end
$var wire 1 . w_RST $end
$var wire 1 / w_K $end
$var wire 4 0 out_UND [3:0] $end
$var wire 1 1 out_DONE $end
$var wire 4 2 out_DEC [3:0] $end
$var wire 4 3 out_CEN [3:0] $end
$scope module acc $end
$var wire 1 ! clk $end
$var wire 1 . rst $end
$var wire 1 ) add $end
$var reg 4 4 N [3:0] $end
$var reg 1 / out_K $end
$upscope $end
$scope module control_BCD $end
$var wire 1 ! clk $end
$var wire 1 / in_K $end
$var wire 1 # in_init $end
$var wire 1 $ rst $end
$var wire 4 5 in_sum_UND [3:0] $end
$var wire 4 6 in_sum_DEC [3:0] $end
$var parameter 4 7 CHECK_NEG $end
$var parameter 4 8 DONE $end
$var parameter 2 9 GE_NEG_ALL $end
$var parameter 2 : GE_NEG_DEC $end
$var parameter 2 ; GE_NEG_NONE $end
$var parameter 2 < GE_NEG_UND $end
$var parameter 4 = ITERATE $end
$var parameter 4 > LAST_SHIFT $end
$var parameter 4 ? LOAD_ALL $end
$var parameter 4 @ LOAD_DEC $end
$var parameter 4 A LOAD_UND $end
$var parameter 4 B PRE_LOAD_ALL $end
$var parameter 4 C PRE_LOAD_DEC $end
$var parameter 4 D PRE_LOAD_UND $end
$var parameter 4 E SHIFT $end
$var parameter 4 F START $end
$var reg 1 1 out_DONE $end
$var reg 1 . out_RST $end
$var reg 1 - out_S1 $end
$var reg 1 , out_S2 $end
$var reg 1 + out_S3 $end
$var reg 1 * out_S4 $end
$var reg 1 ) out_S5 $end
$var reg 4 G state [3:0] $end
$var reg 320 H state_name [320:1] $end
$upscope $end
$scope module lsr_CEN_DEC_UND_BIN $end
$var wire 1 ! clk $end
$var wire 9 I in_BIN [8:0] $end
$var wire 1 . load_BIN $end
$var wire 1 * load_DEC $end
$var wire 1 + load_UND $end
$var wire 1 - shift $end
$var wire 4 J in_UND [3:0] $end
$var wire 4 K in_DEC [3:0] $end
$var reg 4 L out_CEN [3:0] $end
$var reg 4 M out_DEC [3:0] $end
$var reg 4 N out_UND [3:0] $end
$var reg 9 O reg_BIN [8:0] $end
$upscope $end
$scope module mux_DEV $end
$var wire 1 , SELECT $end
$var reg 4 P out [3:0] $end
$upscope $end
$scope module mux_UND $end
$var wire 1 , SELECT $end
$var reg 4 Q out [3:0] $end
$upscope $end
$scope module sum_DEC $end
$var wire 4 R A [3:0] $end
$var wire 4 S B [3:0] $end
$var reg 4 T out [3:0] $end
$upscope $end
$scope module sum_UND $end
$var wire 4 U A [3:0] $end
$var wire 4 V B [3:0] $end
$var reg 4 W out [3:0] $end
$upscope $end
$upscope $end
$upscope $end
$enddefinitions $end
$comment Show the parameter values. $end
$dumpall
b0 F
b1 E
b11 D
b100 C
b101 B
b110 A
b111 @
b1000 ?
b1010 >
b1001 =
b10 <
b11 ;
b1 :
b0 9
b1011 8
b10 7
$end
#0
$dumpvars
bx W
bx V
bx U
bx T
bx S
bx R
bx Q
bx P
bx O
bx N
bx M
bx L
bx K
bx J
b111111111 I
bx H
bx G
bx 6
bx 5
bx 4
bx 3
bx 2
x1
bx 0
x/
x.
x-
x,
x+
x*
x)
bx (
bx '
bx &
bx %
x$
0#
b111111111 "
0!
$end
#10000
b1011 (
b1011 P
b1011 S
b1011 '
b1011 Q
b1011 V
b101001101010100010000010101001001010100 H
01
0)
0*
0+
0,
0-
1.
b0 G
1!
#20000
0/
b1011 &
b1011 6
b1011 K
b1011 T
b1011 %
b1011 5
b1011 J
b1011 W
b1000 4
b0 3
b0 L
b0 2
b0 M
b0 R
b0 0
b0 N
b0 U
b111111111 O
1$
0!
#30000
1!
#40000
0!
#50000
1!
#60000
0$
0!
#70000
1!
#80000
0!
#90000
1#
1!
#100000
0!
#110000
1-
0.
b101001101001000010010010100011001010100 H
b1 G
1!
#120000
b1100 %
b1100 5
b1100 J
b1100 W
b1 0
b1 N
b1 U
b111111110 O
0!
#130000
b10000110100100001000101010000110100101101011111010011100100010101000111 H
0-
0#
b10 G
1!
#140000
0!
#150000
1)
b1001001010101000100010101010010010000010101010001000101 H
b1001 G
1!
#160000
b111 4
0!
#170000
b101001101001000010010010100011001010100 H
0)
1-
b1 G
1!
#180000
b1110 %
b1110 5
b1110 J
b1110 W
b11 0
b11 N
b11 U
b111111100 O
0!
#190000
0-
b10000110100100001000101010000110100101101011111010011100100010101000111 H
b10 G
1!
#200000
0!
#210000
b1001001010101000100010101010010010000010101010001000101 H
1)
b1001 G
1!
#220000
b110 4
0!
#230000
0)
1-
b101001101001000010010010100011001010100 H
b1 G
1!
#240000
b10 %
b10 5
b10 J
b10 W
b111 0
b111 N
b111 U
b111111000 O
0!
#250000
b10000110100100001000101010000110100101101011111010011100100010101000111 H
0-
b10 G
1!
#260000
0!
#270000
b1010 %
b1010 5
b1010 J
b1010 W
b11 &
b11 6
b11 K
b11 T
b11 '
b11 Q
b11 V
b11 (
b11 P
b11 S
1+
1,
b100110001001111010000010100010001011111010101010100111001000100 H
b110 G
1!
#280000
b1101 %
b1101 5
b1101 J
b1101 W
b1010 0
b1010 N
b1010 U
0!
#290000
b1011 &
b1011 6
b1011 K
b1011 T
b101 %
b101 5
b101 J
b101 W
b1011 (
b1011 P
b1011 S
b1011 '
b1011 Q
b1011 V
b1001001010101000100010101010010010000010101010001000101 H
1)
0+
0,
b1001 G
1!
#300000
b101 4
0!
#310000
0)
1-
b101001101001000010010010100011001010100 H
b1 G
1!
#320000
b1100 &
b1100 6
b1100 K
b1100 T
b0 %
b0 5
b0 J
b0 W
b1 2
b1 M
b1 R
b101 0
b101 N
b101 U
b111110000 O
0!
#330000
b10000110100100001000101010000110100101101011111010011100100010101000111 H
0-
b10 G
1!
#340000
0!
#350000
b1000 %
b1000 5
b1000 J
b1000 W
b100 &
b100 6
b100 K
b100 T
b11 '
b11 Q
b11 V
b11 (
b11 P
b11 S
1+
1,
b100110001001111010000010100010001011111010101010100111001000100 H
b110 G
1!
#360000
b1011 %
b1011 5
b1011 J
b1011 W
b1000 0
b1000 N
b1000 U
0!
#370000
b1100 &
b1100 6
b1100 K
b1100 T
b11 %
b11 5
b11 J
b11 W
b1011 (
b1011 P
b1011 S
b1011 '
b1011 Q
b1011 V
b1001001010101000100010101010010010000010101010001000101 H
1)
0+
0,
b1001 G
1!
#380000
b100 4
0!
#390000
0)
1-
b101001101001000010010010100011001010100 H
b1 G
1!
#400000
b1110 &
b1110 6
b1110 K
b1110 T
b1100 %
b1100 5
b1100 J
b1100 W
b11 2
b11 M
b11 R
b1 0
b1 N
b1 U
b111100000 O
0!
#410000
b10000110100100001000101010000110100101101011111010011100100010101000111 H
0-
b10 G
1!
#420000
0!
#430000
1)
b1001001010101000100010101010010010000010101010001000101 H
b1001 G
1!
#440000
b11 4
0!
#450000
b101001101001000010010010100011001010100 H
0)
1-
b1 G
1!
#460000
b1 &
b1 6
b1 K
b1 T
b1110 %
b1110 5
b1110 J
b1110 W
b110 2
b110 M
b110 R
b11 0
b11 N
b11 U
b111000000 O
0!
#470000
0-
b10000110100100001000101010000110100101101011111010011100100010101000111 H
b10 G
1!
#480000
0!
#490000
b110 %
b110 5
b110 J
b110 W
b1001 &
b1001 6
b1001 K
b1001 T
b11 '
b11 Q
b11 V
b11 (
b11 P
b11 S
b100110001001111010000010100010001011111010001000100010101000011 H
1*
1,
b111 G
1!
#500000
b1100 &
b1100 6
b1100 K
b1100 T
b1001 2
b1001 M
b1001 R
0!
#510000
b100 &
b100 6
b100 K
b100 T
b1110 %
b1110 5
b1110 J
b1110 W
b1011 (
b1011 P
b1011 S
b1011 '
b1011 Q
b1011 V
1)
0*
0,
b1001001010101000100010101010010010000010101010001000101 H
b1001 G
1!
#520000
b10 4
0!
#530000
b101001101001000010010010100011001010100 H
0)
1-
b1 G
1!
#540000
b1101 &
b1101 6
b1101 K
b1101 T
b10 %
b10 5
b10 J
b10 W
b1 3
b1 L
b10 2
b10 M
b10 R
b111 0
b111 N
b111 U
b110000000 O
0!
#550000
0-
b10000110100100001000101010000110100101101011111010011100100010101000111 H
b10 G
1!
#560000
0!
#570000
b1010 %
b1010 5
b1010 J
b1010 W
b101 &
b101 6
b101 K
b101 T
b11 '
b11 Q
b11 V
b11 (
b11 P
b11 S
b100110001001111010000010100010001011111010101010100111001000100 H
1+
1,
b110 G
1!
#580000
b1101 %
b1101 5
b1101 J
b1101 W
b1010 0
b1010 N
b1010 U
0!
#590000
b1101 &
b1101 6
b1101 K
b1101 T
b101 %
b101 5
b101 J
b101 W
b1011 (
b1011 P
b1011 S
b1011 '
b1011 Q
b1011 V
1)
0+
0,
b1001001010101000100010101010010010000010101010001000101 H
b1001 G
1!
#600000
b1 4
0!
#610000
b101001101001000010010010100011001010100 H
0)
1-
b1 G
1!
#620000
b0 &
b0 6
b0 K
b0 T
b0 %
b0 5
b0 J
b0 W
b10 3
b10 L
b101 2
b101 M
b101 R
b101 0
b101 N
b101 U
b100000000 O
0!
#630000
0-
b10000110100100001000101010000110100101101011111010011100100010101000111 H
b10 G
1!
#640000
0!
#650000
b1000 %
b1000 5
b1000 J
b1000 W
b1000 &
b1000 6
b1000 K
b1000 T
b11 '
b11 Q
b11 V
b11 (
b11 P
b11 S
b100110001001111010000010100010001011111010000010100110001001100 H
1*
1+
1,
b1000 G
1!
#660000
b1011 &
b1011 6
b1011 K
b1011 T
b1011 %
b1011 5
b1011 J
b1011 W
b1000 2
b1000 M
b1000 R
b1000 0
b1000 N
b1000 U
0!
#670000
b11 &
b11 6
b11 K
b11 T
b11 %
b11 5
b11 J
b11 W
b1011 (
b1011 P
b1011 S
b1011 '
b1011 Q
b1011 V
1)
0*
0+
0,
b1001001010101000100010101010010010000010101010001000101 H
b1001 G
1!
#680000
1/
b0 4
0!
#690000
b1001100010000010101001101010100010111110101001101001000010010010100011001010100 H
0)
1-
b1010 G
1!
#700000
b1100 &
b1100 6
b1100 K
b1100 T
b1100 %
b1100 5
b1100 J
b1100 W
b101 3
b101 L
b1 2
b1 M
b1 R
b1 0
b1 N
b1 U
b0 O
0!
#710000
11
0-
b1000100010011110100111001000101 H
b1011 G
1!
#720000
0!
#730000
b101001101010100010000010101001001010100 H
01
1.
b0 G
1!
#740000
0/
b1011 &
b1011 6
b1011 K
b1011 T
b1011 %
b1011 5
b1011 J
b1011 W
b1000 4
b0 3
b0 L
b0 2
b0 M
b0 R
b0 0
b0 N
b0 U
b111111111 O
0!
